brawny/__init__.py
brawny/_context.py
brawny/accounts.py
brawny/api.py
brawny/async_runtime.py
brawny/automation.py
brawny/chain.py
brawny/cli_templates.py
brawny/error_taxonomy.py
brawny/history.py
brawny/http.py
brawny/interfaces.py
brawny/invariants.py
brawny/keystore.py
brawny/lifecycle.py
brawny/logging.py
brawny/logging_types.py
brawny/metrics.py
brawny/multicall.py
brawny/network_guard.py
brawny/runtime_controls.py
brawny/script_tx.py
brawny/scripting.py
brawny/startup.py
brawny/telegram.py
brawny/testing.py
brawny/timeout.py
brawny/tx_hash.py
brawny/types.py
brawny/utils.py
brawny/validation.py
brawny/_rpc/__init__.py
brawny/_rpc/broadcast.py
brawny/_rpc/caller.py
brawny/_rpc/client.py
brawny/_rpc/clients.py
brawny/_rpc/context.py
brawny/_rpc/errors.py
brawny/_rpc/gas.py
brawny/_rpc/pool.py
brawny/_rpc/retry.py
brawny/_rpc/retry_policy.py
brawny/_rpc/transport.py
brawny/alerts/__init__.py
brawny/alerts/abi_resolver.py
brawny/alerts/base.py
brawny/alerts/context.py
brawny/alerts/contracts.py
brawny/alerts/encoded_call.py
brawny/alerts/errors.py
brawny/alerts/events.py
brawny/alerts/function_caller.py
brawny/alerts/health.py
brawny/alerts/routing.py
brawny/alerts/send.py
brawny/assets/AGENTS.md
brawny/cli/__init__.py
brawny/cli/app.py
brawny/cli/bootstrap.py
brawny/cli/helpers.py
brawny/cli/commands/__init__.py
brawny/cli/commands/abi.py
brawny/cli/commands/accounts.py
brawny/cli/commands/console.py
brawny/cli/commands/contract.py
brawny/cli/commands/controls.py
brawny/cli/commands/health.py
brawny/cli/commands/init_project.py
brawny/cli/commands/intents.py
brawny/cli/commands/job_dev.py
brawny/cli/commands/jobs.py
brawny/cli/commands/logs.py
brawny/cli/commands/maintenance.py
brawny/cli/commands/migrate.py
brawny/cli/commands/networks.py
brawny/cli/commands/run.py
brawny/cli/commands/script.py
brawny/cli/commands/signer.py
brawny/config/__init__.py
brawny/config/models.py
brawny/config/parser.py
brawny/config/routing.py
brawny/config/validation.py
brawny-0.1.42.dist-info/METADATA
brawny-0.1.42.dist-info/WHEEL
brawny-0.1.42.dist-info/entry_points.txt
brawny-0.1.42.dist-info/top_level.txt
brawny-0.1.42.dist-info/RECORD
