Metadata-Version: 2.4
Name: brawny
Version: 0.1.42
Summary: Block-driven Ethereum job/transaction execution framework
Author-email: yearn <dev@yearn.fi>
License: MIT
Project-URL: Homepage, https://github.com/yearn/brawny
Project-URL: Documentation, https://github.com/yearn/brawny#readme
Project-URL: Repository, https://github.com/yearn/brawny.git
Project-URL: Issues, https://github.com/yearn/brawny/issues
Keywords: ethereum,web3,blockchain,jobs,transactions
Classifier: Development Status :: 3 - Alpha
Classifier: Intended Audience :: Developers
Classifier: License :: OSI Approved :: MIT License
Classifier: Operating System :: OS Independent
Classifier: Programming Language :: Python :: 3
Classifier: Programming Language :: Python :: 3.10
Classifier: Programming Language :: Python :: 3.11
Classifier: Programming Language :: Python :: 3.12
Classifier: Topic :: Software Development :: Libraries :: Python Modules
Requires-Python: >=3.10
Requires-Dist: eth-account<0.14,>=0.13
Requires-Dist: web3<8.0,>=7.0
Requires-Dist: click<9.0,>=8.1
Requires-Dist: pyyaml<7.0,>=6.0
Requires-Dist: python-dotenv<2.0,>=1.0
Requires-Dist: structlog<25.0,>=24.1
Requires-Dist: httpx<1.0,>=0.26
Requires-Dist: rich<14.0,>=13.0
Requires-Dist: prometheus-client<1.0,>=0.20
Requires-Dist: prompt_toolkit<4.0,>=3.0
Requires-Dist: pygments<3.0,>=2.17
Requires-Dist: cachetools<6.0,>=5.0
Provides-Extra: dev
Requires-Dist: pytest<9.0,>=8.0; extra == "dev"
Requires-Dist: pytest-asyncio<1.0,>=0.23; extra == "dev"
Requires-Dist: pytest-cov<5.0,>=4.1; extra == "dev"
Requires-Dist: mypy<2.0,>=1.8; extra == "dev"
Requires-Dist: ruff<1.0,>=0.2; extra == "dev"
Requires-Dist: black<25.0,>=24.1; extra == "dev"
Requires-Dist: pre-commit<4.0,>=3.6; extra == "dev"
Provides-Extra: test
Requires-Dist: pytest<9.0,>=8.0; extra == "test"
Requires-Dist: pytest-asyncio<1.0,>=0.23; extra == "test"
Requires-Dist: pytest-cov<5.0,>=4.1; extra == "test"
